Workbook

Sheet Sign-Off Summary
A1: Tummly UK Pricing & Billing — Production Sign-off v3.0
A2: APPROVED FOR DEVELOPMENT · UK only · GBP · 20% VAT · Audited 2026-08-06
A4: Plan | B4: Billing | C4: Net price | D4: VAT | E4: Gross | F4: Locations | G4: Users | H4: AI | I4: Email | J4: SMS | K4: Starter kit | L4: Status
A5: Pilot | B5: 30 days | C5: 0 | D5: 0 | E5: 0 | F5: 1 | G5: 2 | H5: 20 | I5: 500 | J5: 20 | K5: One/account lifetime | L5: Approved
A6: Starter | B6: Monthly | C6: 39 | D6: 7.8 | E6: 46.8 | F6: 1 | G6: 3 | H6: 100 | I6: 2500 | J6: 100 | K6: If not used in Pilot | L6: Approved
A7: Growth | B7: Monthly | C7: 99 | D7: 19.8 | E7: 118.8 | F7: 3 | G7: 10 | H7: 500 | I7: 10000 | J7: 350 | K7: If not used in Pilot | L7: Approved
A8: Group | B8: Monthly | C8: 199 | D8: 39.8 | E8: 238.8 | F8: 5 | G8: 25 | H8: 1500 | I8: 25000 | J8: 700 | K8: If not used in Pilot | L8: Approved
A9: Additional Group Location | B9: Monthly | C9: 39 | D9: 7.8 | E9: 46.8 | F9: 1 | G9: 2 | H9: 100 | I9: 5000 | J9: 100 | K9: No extra free kit | L9: Approved
A12: Development instruction | B12: Proceed. Do not wait for another commercial decision. Campaign Email must use the provider adapter and must not use shared Resend Broadcast Contacts as tenant guest truth.

Sheet Assumptions
A1: Commercial, Cost and Scenario Assumptions
A2: Blue text is a hardcoded commercial input. Green source cells cite current official or internal references. Yellow cells are factual deployment values.
A4: Key | B4: Value | C4: Unit | D4: Status | E4: Purpose | F4: Source | G4: Owner | H4: Notes
A5: VAT_RATE | B5: 0.2 | C5: % | D5: Approved | E5: UK VAT | F5: https://www.gov.uk/vat-rates | G5: Amin | H5: Exclusive pricing
A6: STRIPE_CARD_PCT | B6: 0.015 | C6: % gross | D6: External | E6: Payments | F6: https://stripe.com/gb/pricing | G6: Salman | H6: Standard UK cards
A7: STRIPE_CARD_FIXED | B7: 0.2 | C7: GBP/payment | D7: External | E7: Payments | F7: https://stripe.com/gb/pricing | G7: Salman | H7: Per successful payment
A8: STRIPE_BILLING_PCT | B8: 0.007 | C8: % Billing volume | D8: External | E8: Recurring billing | F8: https://stripe.com/gb/billing/pricing | G8: Salman | H8: Pay as you go
A9: SMS_COST | B9: 0.06 | C9: GBP/segment | D9: Approved reserve | E9: SMS COGS | F9: https://www.twilio.com/en-us/sms/pricing/gb | G9: Amin | H9: Includes FX/carrier variance buffer
A10: AI_COST | B10: 0.003 | C10: GBP/action | D10: Approved reserve | E10: AI COGS | F10: Tummly channel cost analysis | G10: Amin | H10: Blended completed action
A11: EMAIL_COST | B11: 0.001 | C11: GBP/recipient | D11: Approved reserve | E11: Email COGS | F11: Tummly channel cost analysis + provider adapter buffer | G11: Amin | H11: Not Resend Broadcast contact pricing
A12: BASE_SUPPORT_ACCOUNT | B12: 10 | C12: GBP/account-month | D12: Internal budget | E12: Support/ops | F12: Commercial planning budget | G12: Amin | H12: Base scenario
A13: BASE_SUPPORT_LOCATION | B13: 4 | C13: GBP/additional location-month | D13: Internal budget | E13: Support/ops | F13: Commercial planning budget | G13: Amin | H13: Base scenario
A14: LOW_PLATFORM_FIXED | B14: 250 | C14: GBP/month | D14: Scenario | E14: Shared platform | F14: Commercial stress test | G14: Amin | H14: Low
A15: BASE_PLATFORM_FIXED | B15: 500 | C15: GBP/month | D15: Scenario | E15: Shared platform | F15: Commercial stress test | G15: Amin | H15: Base
A16: HIGH_PLATFORM_FIXED | B16: 1000 | C16: GBP/month | D16: Scenario | E16: Shared platform | F16: Commercial stress test | G16: Amin | H16: High
... A26: DORMANT_RETENTION | B26: 90 | C26: days | D26: Approved v1 | E26: Account lifecycle | F26: Commercial policy | G26: Amin | H26: Subject to product retention policy
A27: VAT_NUMBER | B27: INSERT BEFORE LIVE CHARGE | C27: text | D27: Deployment value | E27: VAT invoice | F27: HMRC certificate | G27: Operations | H27: Checkout fails closed if missing
A28: VAT_EFFECTIVE_DATE | B28: INSERT BEFORE LIVE CHARGE | C28: date | D28: Deployment value | E28: VAT invoice | F28: HMRC certificate | G28: Operations | H28: Checkout fails closed if missing

Sheet Plan Economics
A1: Plan Unit Economics
A2: Full-use and expected-use contribution. VAT is not revenue. Shared fixed platform cost is analysed separately.
A4: Plan | B4: Net/month | C4: VAT | D4: Gross | E4: Locations | F4: AI | G4: Email | H4: SMS | I4: Payment + Billing | J4: AI COGS | K4: Email COGS | L4: SMS COGS | M4: Variable contribution | N4: Variable margin | O4: Support budget | P4: Contribution after support | Q4: Margin after support | R4: Expected contribution after support | S4: Expected margin | T4: Annual net
A5: Pilot | B5: 0 | C5: =B5*Assumptions!$B$5 | D5: =B5+C5 | E5: 1 | F5: 20 | G5: 500 | H5: 20 | I5: =IF(B5=0,0,D5*(Assumptions!$B$6+Assumptions!$B$8)+Assumptions!$B$7) | J5: =F5*Assumptions!$B$10 | K5: =G5*Assumptions!$B$11 | L5: =H5*Assumptions!$B$9 | M5: =B5-I5-J5-K5-L5 | N5: =IF(B5=0,0,M5/B5) | O5: 0 | P5: =M5-O5 | Q5: =IF(B5=0,0,P5/B5) | R5: =B5-I5-(J5+K5+L5)*Assumptions!$B$17-O5 | S5: =IF(B5=0,0,R5/B5) | T5: 0
A6: Starter | B6: 39 | C6: =B6*Assumptions!$B$5 | D6: =B6+C6 | E6: 1 | F6: 100 | G6: 2500 | H6: 100 | I6: =IF(B6=0,0,D6*(Assumptions!$B$6+Assumptions!$B$8)+Assumptions!$B$7) | J6: =F6*Assumptions!$B$10 | K6: =G6*Assumptions!$B$11 | L6: =H6*Assumptions!$B$9 | M6: =B6-I6-J6-K6-L6 | N6: =IF(B6=0,0,M6/B6) | O6: 10 | P6: =M6-O6 | Q6: =IF(B6=0,0,P6/B6) | R6: =B6-I6-(J6+K6+L6)*Assumptions!$B$17-O6 | S6: =IF(B6=0,0,R6/B6) | T6: 398
A7: Growth | B7: 99 | C7: =B7*Assumptions!$B$5 | D7: =B7+C7 | E7: 3 | F7: 500 | G7: 10000 | H7: 350 | I7: =IF(B7=0,0,D7*(Assumptions!$B$6+Assumptions!$B$8)+Assumptions!$B$7) | J7: =F7*Assumptions!$B$10 | K7: =G7*Assumptions!$B$11 | L7: =H7*Assumptions!$B$9 | M7: =B7-I7-J7-K7-L7 | N7: =IF(B7=0,0,M7/B7) | O7: 10 | P7: =M7-O7 | Q7: =IF(B7=0,0,P7/B7) | R7: =B7-I7-(J7+K7+L7)*Assumptions!$B$17-O7 | S7: =IF(B7=0,0,R7/B7) | T7: 1010
A8: Group | B8: 199 | C8: =B8*Assumptions!$B$5 | D8: =B8+C8 | E8: 5 | F8: 1500 | G8: 25000 | H8: 700 | I8: =IF(B8=0,0,D8*(Assumptions!$B$6+Assumptions!$B$8)+Assumptions!$B$7) | J8: =F8*Assumptions!$B$10 | K8: =G8*Assumptions!$B$11 | L8: =H8*Assumptions!$B$9 | M8: =B8-I8-J8-K8-L8 | N8: =IF(B8=0,0,M8/B8) | O8: 10 | P8: =M8-O8 | Q8: =IF(B8=0,0,P8/B8) | R8: =B8-I8-(J8+K8+L8)*Assumptions!$B$17-O8 | S8: =IF(B8=0,0,R8/B8) | T8: 2030
A9: Additional Group Location | B9: 39 | C9: =B9*Assumptions!$B$5 | D9: =B9+C9 | E9: 1 | F9: 100 | G9: 5000 | H9: 100 | I9: =IF(B9=0,0,D9*(Assumptions!$B$6+Assumptions!$B$8)+Assumptions!$B$7) | J9: =F9*Assumptions!$B$10 | K9: =G9*Assumptions!$B$11 | L9: =H9*Assumptions!$B$9 | M9: =B9-I9-J9-K9-L9 | N9: =IF(B9=0,0,M9/B9) | O9: 4 | P9: =M9-O9 | Q9: =IF(B9=0,0,P9/B9) | R9: =B9-I9-(J9+K9+L9)*Assumptions!$B$17-O9 | S9: =IF(B9=0,0,R9/B9) | T9: 398

Sheet Top-Up Economics
A1: Top-Up Pack Economics
A2: Net prices exclude VAT. Contribution includes conservative channel COGS and standard UK Stripe + Billing fees.
A4: Channel | B4: Quantity | C4: Net | D4: VAT | E4: Gross | F4: Net/unit | G4: Unit cost | H4: Channel COGS | I4: Payment + Billing | J4: Contribution | K4: Margin | L4: Access | M4: Validity | N4: Lookup key
A5: AI | B5: 100 | C5: 5 | D5: =C5*Assumptions!$B$5 | E5: =C5+D5 | F5: =C5/B5 | G5: =Assumptions!$B$10 | H5: =B5*G5 | I5: =E5*(Assumptions!$B$6+Assumptions!$B$8)+Assumptions!$B$7 | J5: =C5-H5-I5 | K5: =J5/C5 | L5: Paid | M5: 12 months | N5: tummly_ai_100_gbp_v3
A6: AI | B6: 500 | C6: 15 | D6: =C6*Assumptions!$B$5 | E6: =C6+D6 | F6: =C6/B6 | G6: =Assumptions!$B$10 | H6: =B6*G6 | I6: =E6*(Assumptions!$B$6+Assumptions!$B$8)+Assumptions!$B$7 | J6: =C6-H6-I6 | K6: =J6/C6 | L6: Paid | M6: 12 months | N6: tummly_ai_500_gbp_v3
A7: AI | B7: 2000 | C7: 39 | D7: =C7*Assumptions!$B$5 | E7: =C7+D7 | F7: =C7/B7 | G7: =Assumptions!$B$10 | H7: =B7*G7 | I7: =E7*(Assumptions!$B$6+Assumptions!$B$8)+Assumptions!$B$7 | J7: =C7-H7-I7 | K7: =J7/C7 | L7: Paid | M7: 12 months | N7: tummly_ai_2000_gbp_v3
A8: Email | B8: 5000 | C8: 10 | D8: =C8*Assumptions!$B$5 | E8: =C8+D8 | F8: =C8/B8 | G8: =Assumptions!$B$11 | H8: =B8*G8 | I8: =E8*(Assumptions!$B$6+Assumptions!$B$8)+Assumptions!$B$7 | J8: =C8-H8-I8 | K8: =J8/C8 | L8: Paid | M8: 12 months | N8: tummly_email_5000_gbp_v3
A9: Email | B9: 20000 | C9: 30 | D9: =C9*Assumptions!$B$5 | E9: =C9+D9 | F9: =C9/B9 | G9: =Assumptions!$B$11 | H9: =B9*G9 | I9: =E9*(Assumptions!$B$6+Assumptions!$B$8)+Assumptions!$B$7 | J9: =C9-H9-I9 | K9: =J9/C9 | L9: Paid | M9: 12 months | N9: tummly_email_20000_gbp_v3
A10: Email | B10: 50000 | C10: 60 | D10: =C10*Assumptions!$B$5 | E10: =C10+D10 | F10: =C10/B10 | G10: =Assumptions!$B$11 | H10: =B10*G10 | I10: =E10*(Assumptions!$B$6+Assumptions!$B$8)+Assumptions!$B$7 | J10: =C10-H10-I10 | K10: =J10/C10 | L10: Paid | M10: 12 months | N10: tummly_email_50000_gbp_v3
A11: SMS | B11: 100 | C11: 12 | D11: =C11*Assumptions!$B$5 | E11: =C11+D11 | F11: =C11/B11 | G11: =Assumptions!$B$9 | H11: =B11*G11 | I11: =E11*(Assumptions!$B$6+Assumptions!$B$8)+Assumptions!$B$7 | J11: =C11-H11-I11 | K11: =J11/C11 | L11: Paid | M11: 12 months | N11: tummly_sms_100_gbp_v3
A12: SMS | B12: 500 | C12: 55 | D12: =C12*Assumptions!$B$5 | E12: =C12+D12 | F12: =C12/B12 | G12: =Assumptions!$B$9 | H12: =B12*G12 | I12: =E12*(Assumptions!$B$6+Assumptions!$B$8)+Assumptions!$B$7 | J12: =C12-H12-I12 | K12: =J12/C12 | L12: Paid | M12: 12 months | N12: tummly_sms_500_gbp_v3
A13: SMS | B13: 1000 | C13: 100 | D13: =C13*Assumptions!$B$5 | E13: =C13+D13 | F13: =C13/B13 | G13: =Assumptions!$B$9 | H13: =B13*G13 | I13: =E13*(Assumptions!$B$6+Assumptions!$B$8)+Assumptions!$B$7 | J13: =C13-H13-I13 | K13: =J13/C13 | L13: Paid | M13: 12 months | N13: tummly_sms_1000_gbp_v3
A14: SMS | B14: 5000 | C14: 450 | D14: =C14*Assumptions!$B$5 | E14: =C14+D14 | F14: =C14/B14 | G14: =Assumptions!$B$9 | H14: =B14*G14 | I14: =E14*(Assumptions!$B$6+Assumptions!$B$8)+Assumptions!$B$7 | J14: =C14-H14-I14 | K14: =J14/C14 | L14: Group/approval | M14: 12 months | N14: tummly_sms_5000_gbp_v3

Sheet Scenario Model
A1: Operating Scenario and Break-Even Model
A2: Tests paid-account contribution after support against shared fixed platform cost. Plan mix and assumptions are editable on Assumptions.
A4: Scenario | B4: Usage | C4: Support/account | D4: Fixed platform | E4: Starter contribution | F4: Growth contribution | G4: Group contribution | H4: Weighted contribution/account | I4: Break-even paid accounts | J4: 20 paid accounts | K4: 50 paid accounts | L4: 100 paid accounts | M4: Status | N4: Notes
A5: Low cost / low use | B5: 0.35 | C5: 5 | D5: 250 | E5: ='Plan Economics'!B6-'Plan Economics'!I6-('Plan Economics'!J6+'Plan Economics'!K6+'Plan Economics'!L6)*B5-C5 | F5: ='Plan Economics'!B7-'Plan Economics'!I7-('Plan Economics'!J7+'Plan Economics'!K7+'Plan Economics'!L7)*B5-C5 | G5: ='Plan Economics'!B8-'Plan Economics'!I8-('Plan Economics'!J8+'Plan Economics'!K8+'Plan Economics'!L8)*B5-C5 | H5: =E5*Assumptions!$B$22+F5*Assumptions!$B$23+G5*Assumptions!$B$24 | I5: =IF(H5<=0,"—",D5/H5) | J5: =H5*20-D5 | K5: =H5*50-D5 | L5: =H5*100-D5 | M5: =IF(H5>0,"Contribution-positive","Review") | N5: Excludes starter-kit acquisition and founder salary
A6: Base | B6: 0.5 | C6: 10 | D6: 500 | E6: ='Plan Economics'!B6-'Plan Economics'!I6-('Plan Economics'!J6+'Plan Economics'!K6+'Plan Economics'!L6)*B6-C6 | F6: ='Plan Economics'!B7-'Plan Economics'!I7-('Plan Economics'!J7+'Plan Economics'!K7+'Plan Economics'!L7)*B6-C6 | G6: ='Plan Economics'!B8-'Plan Economics'!I8-('Plan Economics'!J8+'Plan Economics'!K8+'Plan Economics'!L8)*B6-C6 | H6: =E6*Assumptions!$B$22+F6*Assumptions!$B$23+G6*Assumptions!$B$24 | I6: =IF(H6<=0,"—",D6/H6) | J6: =H6*20-D6 | K6: =H6*50-D6 | L6: =H6*100-D6 | M6: =IF(H6>0,"Contribution-positive","Review") | N6: Excludes starter-kit acquisition and founder salary
A7: High cost / high use | B7: 0.75 | C7: 20 | D7: 1000 | E7: ='Plan Economics'!B6-'Plan Economics'!I6-('Plan Economics'!J6+'Plan Economics'!K6+'Plan Economics'!L6)*B7-C7 | F7: ='Plan Economics'!B7-'Plan Economics'!I7-('Plan Economics'!J7+'Plan Economics'!K7+'Plan Economics'!L7)*B7-C7 | G7: ='Plan Economics'!B8-'Plan Economics'!I8-('Plan Economics'!J8+'Plan Economics'!K8+'Plan Economics'!L8)*B7-C7 | H7: =E7*Assumptions!$B$22+F7*Assumptions!$B$23+G7*Assumptions!$B$24 | I7: =IF(H7<=0,"—",D7/H7) | J7: =H7*20-D7 | K7: =H7*50-D7 | L7: =H7*100-D7 | M7: =IF(H7>0,"Contribution-positive","Review") | N7: Excludes starter-kit acquisition and founder salary

Sheet Pilot Economics
A1: Pilot Acquisition and Payback
A2: Pilot cost is a commercial acquisition subsidy. The physical kit must remain qualified and limited to one per Billing Account lifetime.
A4: Metric | B4: Formula / input | C4: Value | D4: Unit | E4: 15% conversion | F4: 25% conversion | G4: 35% conversion | H4: Starter expected contribution | I4: Payback at 15% | J4: Payback at 25% | K4: Payback at 35% | L4: Decision
A5: Starter-kit cap | B5: Assumptions | C5: 25 | D5: GBP | L5: Approved
A6: Pilot onboarding budget | B6: Assumptions | C6: 15 | D6: GBP | L6: Approved
A7: Pilot channel COGS | B7: 20 AI + 500 Email + 20 SMS | C7: 1.76 | D7: GBP | L7: Calculated
A8: Total Pilot subsidy | B8: Kit + onboarding + full channel use | C8: =SUM(C5:C7)
A10: Acquisition subsidy per converted account | E10: =$C$8/15% | F10: =$C$8/25% | G10: =$C$8/35% | H10: ='Plan Economics'!R6 | I10: =E10/H10 | J10: =F10/H10 | K10: =G10/H10 | L10: =IF(J10<=9,"Acceptable","Review")
A12: Operational rule | B12: Do not dispatch a physical kit until the Pilot is qualified. If landed cost exceeds £25, reduce pack scope or obtain a lower quote.

Sheet Burn Rates
A1: Credit Burn Rates
A2: Authoritative successful events only. Failed, skipped and idempotently prevented actions consume zero.
A4: Action | B4: AI | C4: Email | D4: SMS | E4: Charge event | F4: Zero-charge case | G4: Reservation | H4: Provider | I4: Ledger reference | J4: Status
A5: Automatic Feedback classification | B5: 0 | C5: 0 | D5: 0 | E5: None | F5: All | G5: No | H5: Azure OpenAI | I5: feedback_id | J5: Approved
A6: Standard scheduled Weekly Brief | B6: 0 | C6: 0 | D6: 0 | E6: None | F6: All | G6: No | H6: Azure OpenAI | I6: brief_id | J6: Approved
A7: AI Assistant answer | B7: 1 | C7: 0 | D7: 0 | E7: Usable answer returned | F7: Failure/timeout/blocked | G7: No | H7: Azure OpenAI | I7: conversation_id | J7: Approved
A8: Recovery AI Draft | B8: 1 | C8: 0 | D8: 0 | E8: Usable Draft returned | F8: Failure/timeout/blocked | G8: No | H8: Azure OpenAI | I8: feedback_id | J8: Approved
A9: Campaign AI Draft | B9: 1 | C9: 0 | D9: 0 | E9: Usable Draft returned | F9: Failure/timeout/blocked | G9: No | H9: Azure OpenAI | I9: campaign_id | J9: Approved
A10: Regenerate | B10: 1 | C10: 0 | D10: 0 | E10: New usable output | F10: Failure/timeout/blocked | G10: No | H10: Azure OpenAI | I10: source_output_id | J10: Approved
A11: Recovery Email | B11: 0 | C11: 0 | D11: 0 | E11: Provider accepted | F11: Invalid/suppressed/ineligible | G11: No | H11: Resend Email API | I11: feedback_id | J11: Approved
A12: Campaign Email recipient | B12: 0 | C12: 1 | D12: 0 | E12: Provider accepted | F12: Skipped before submission | G12: Yes | H12: CampaignEmailProvider | I12: campaign_recipient_id | J12: Approved
A13: Recovery SMS segment | B13: 0 | C13: 0 | D13: 1 | E13: Segment accepted | F13: Skipped before submission | G13: Yes | H13: Twilio UK | I13: message_id | J13: Approved
A14: Campaign SMS segment | B14: 0 | C14: 0 | D14: 1 | E14: Segment accepted | F14: Skipped before submission | G14: Yes | H14: Twilio UK | I14: campaign_recipient_id | J14: Approved

Sheet Billing Rules
A1: Production Billing and Lifecycle Rules
A2: Server-enforced rules with explicit states, permissions and audit.
A4: Area | B4: Rule | C4: Server implementation | D4: Operator experience | E4: Audit | F4: Owner | G4: Status
A5: UK scope | B5: GB and GBP only | C5: Reject unsupported account/Location country | D5: No international selector | E5: Account setup | F5: Product | G5: Approved
A6: VAT | B6: 20% exclusive | C6: Pence storage; invoice-line rounding; fail closed without VAT values | D6: Show net, VAT and gross | E6: Invoice/tax config | F6: Operations | G6: Approved
A7: Pilot start | B7: Activation, not signup | C7: Create one-time entitlement on activation | D7: Show exact end date | E7: Activation event | F7: Product | G7: Approved
A8: Starter kit | B8: One/account lifetime | C8: Unique entitlement record and dispatch gate | D8: Show fulfilled/not eligible | E8: Fulfilment event | F8: Operations | G8: Approved
A9: Included credits | B9: Anniversary; no rollover | C9: Allocate only after paid renewal or active annual state | D9: Show reset date | E9: Allocation ledger | F9: Engineering | G9: Approved
A10: Top-ups | B10: 12 months; FEFO | C10: Expiry-aware allocation ledger | D10: Show expiry | E10: Top-up ledger | F10: Engineering | G10: Approved
A11: Campaign reservation | B11: Atomic full estimate | C11: Transactional reserve, settle, release | D11: Show before/after balance | E11: Reservation ledger | F11: Engineering | G11: Approved
A12: Skipped recipient | B12: Zero charge | C12: Remove before submission | D12: Show skipped count | E12: Recipient outcome | F12: Engineering | G12: Approved
A13: Partial send | B13: Explicit state | C13: Idempotent reviewed retry | D13: Show accepted/failed/not attempted | E13: Campaign audit | F13: Engineering | G13: Approved
A14: Provider email | B14: Adapter, not shared Broadcast Contacts | C14: Tenant-scoped suppression/unsubscribe | D14: No provider-specific complexity | E14: Provider config | F14: Engineering | G14: Approved
A15: Upgrade | B15: Immediate, prorated | C15: Positive incremental allowance only | D15: Show immediate charge | E15: Subscription event | F15: Billing | G15: Approved
... A18: Pricebook | B18: Immutable and versioned | C18: New Prices for future changes | D18: Contracted price retained | E18: Pricebook event | F18: Engineering | G18: Approved

Sheet Stripe Pricebook
A1: Stripe Product and Price Catalogue
A2: Create new immutable Stripe Prices. Insert live IDs after creation. Do not edit active Price amounts.
A4: Type | B4: Public name | C4: Lookup key | D4: Interval | E4: Net pence | F4: Net GBP | G4: VAT | H4: Gross | I4: Live Stripe Price ID
A5: Subscription | B5: Starter monthly | C5: tummly_starter_monthly_gbp_v3 | D5: month | E5: 3900 | F5: =E5/100 | G5: =F5*Assumptions!$B$5 | H5: =F5+G5 | I5: INSERT AFTER STRIPE CREATION
A6: Subscription | B6: Starter annual | C6: tummly_starter_annual_gbp_v3 | D6: year | E6: 39800 | F6: =E6/100 | G6: =F6*Assumptions!$B$5 | H6: =F6+G6 | I6: INSERT AFTER STRIPE CREATION
A7: Subscription | B7: Growth monthly | C7: tummly_growth_monthly_gbp_v3 | D7: month | E7: 9900 | F7: =E7/100 | G7: =F7*Assumptions!$B$5 | H7: =F7+G7 | I7: INSERT AFTER STRIPE CREATION
A8: Subscription | B8: Growth annual | C8: tummly_growth_annual_gbp_v3 | D8: year | E8: 101000 | F8: =E8/100 | G8: =F8*Assumptions!$B$5 | H8: =F8+G8 | I8: INSERT AFTER STRIPE CREATION
A9: Subscription | B9: Group monthly | C9: tummly_group_monthly_gbp_v3 | D9: month | E9: 19900 | F9: =E9/100 | G9: =F9*Assumptions!$B$5 | H9: =F9+G9 | I9: INSERT AFTER STRIPE CREATION
A10: Subscription | B10: Group annual | C10: tummly_group_annual_gbp_v3 | D10: year | E10: 203000 | F10: =E10/100 | G10: =F10*Assumptions!$B$5 | H10: =F10+G10 | I10: INSERT AFTER STRIPE CREATION
A11: Subscription | B11: Additional Group Location monthly | C11: tummly_group_location_monthly_gbp_v3 | D11: month | E11: 3900 | F11: =E11/100 | G11: =F11*Assumptions!$B$5 | H11: =F11+G11 | I11: INSERT AFTER STRIPE CREATION
A12: Subscription | B12: Additional Group Location annual | C12: tummly_group_location_annual_gbp_v3 | D12: year | E12: 39800 | F12: =E12/100 | G12: =F12*Assumptions!$B$5 | H12: =F12+G12 | I12: INSERT AFTER STRIPE CREATION
A13: One-time | B13: 100 AI actions | C13: tummly_ai_100_gbp_v3 | D13: one_time | E13: 500 | F13: =E13/100 | G13: =F13*Assumptions!$B$5 | H13: =F13+G13 | I13: INSERT AFTER STRIPE CREATION
A14: One-time | B14: 500 AI actions | C14: tummly_ai_500_gbp_v3 | D14: one_time | E14: 1500 | F14: =E14/100 | G14: =F14*Assumptions!$B$5 | H14: =F14+G14 | I14: INSERT AFTER STRIPE CREATION
A15: One-time | B15: 2,000 AI actions | C15: tummly_ai_2000_gbp_v3 | D15: one_time | E15: 3900 | F15: =E15/100 | G15: =F15*Assumptions!$B$5 | H15: =F15+G15 | I15: INSERT AFTER STRIPE CREATION
A16: One-time | B16: 5,000 Email credits | C16: tummly_email_5000_gbp_v3 | D16: one_time | E16: 1000 | F16: =E16/100 | G16: =F16*Assumptions!$B$5 | H16: =F16+G16 | I16: INSERT AFTER STRIPE CREATION
... A22: One-time | B22: 5,000 SMS segments | C22: tummly_sms_5000_gbp_v3 | D22: one_time | E22: 45000 | F22: =E22/100 | G22: =F22*Assumptions!$B$5 | H22: =F22+G22 | I22: INSERT AFTER STRIPE CREATION

Sheet Audit Controls
A1: Automated Cross-File and Model Controls
A2: These controls document the final audit tests. PASS is required before handoff.
A4: Control | B4: Expected | C4: Actual / formula | D4: Result | E4: Severity | F4: Owner | G4: Notes
A5: Plan mix totals 100% | B5: 100% | C5: =Assumptions!B22+Assumptions!B23+Assumptions!B24 | D5: =IF(ABS(C5-1)<0.000001,"PASS","FAIL") | E5: High | F5: Commercial | G5: Scenario validity
A6: VAT rate | B6: 20% | C6: =Assumptions!B5 | D6: =IF(ABS(C6-20%)<0.000001,"PASS","FAIL") | E6: Critical | F6: Operations | G6: UK launch
A7: Starter gross | B7: £46.80 | C7: ='Plan Economics'!D6 | D7: =IF(ABS(C7-46.8)<0.01,"PASS","FAIL") | E7: High | F7: Billing | G7: 39 + VAT
A8: Growth gross | B8: £118.80 | C8: ='Plan Economics'!D7 | D8: =IF(ABS(C8-118.8)<0.01,"PASS","FAIL") | E8: High | F8: Billing | G8: 99 + VAT
A9: Group gross | B9: £238.80 | C9: ='Plan Economics'!D8 | D9: =IF(ABS(C9-238.8)<0.01,"PASS","FAIL") | E9: High | F9: Billing | G9: 199 + VAT
A10: No negative top-up contribution | B10: > £0 | C10: =MIN('Top-Up Economics'!J5:J14) | D10: =IF(C10>0,"PASS","FAIL") | E10: Critical | F10: Commercial | G10: Pack viability
A11: Starter variable margin positive | B11: > 0% | C11: ='Plan Economics'!N6 | D11: =IF(C11>0,"PASS","FAIL") | E11: High | F11: Commercial | G11: Full use
A12: Growth variable margin positive | B12: > 0% | C12: ='Plan Economics'!N7 | D12: =IF(C12>0,"PASS","FAIL") | E12: High | F12: Commercial | G12: Full use
A13: Group variable margin positive | B13: > 0% | C13: ='Plan Economics'!N8 | D13: =IF(C13>0,"PASS","FAIL") | E13: High | F13: Commercial | G13: Full use
A14: Base scenario break-even finite | B14: > 0 | C14: ='Scenario Model'!I6 | D14: =IF(C14>0,"PASS","FAIL") | E14: High | F14: Commercial | G14: Base case

Sheet Source Register
A1: Source Register
A2: Official sources checked during final audit, plus internal Tummly source records.
A4: Source | B4: Purpose | C4: URL / record | D4: Checked | E4: Finding | F4: Applied change
A5: HMRC VAT rates | B5: UK VAT rate | C5: https://www.gov.uk/vat-rates | D5: 2026-08-06 | E5: Standard rate 20% | F5: VAT config
A6: HMRC VAT registration | B6: Registration/effective date | C6: https://www.gov.uk/register-for-vat | D6: 2026-08-06 | E6: Real VAT details required | F6: Fail-closed go-live
A7: HMRC invoices | B7: VAT invoice fields | C7: https://www.gov.uk/invoicing-and-taking-payment-from-customers/invoices-what-they-must-include | D7: 2026-08-06 | E7: Invoice requirements | F7: Invoice specification
A8: Stripe Payments UK | B8: Card fees | C8: https://stripe.com/gb/pricing | D8: 2026-08-06 | E8: 1.5% + 20p UK cards | F8: Unit economics
A9: Stripe Billing | B9: Billing fee | C9: https://stripe.com/gb/billing/pricing | D9: 2026-08-06 | E9: 0.7% Billing volume | F9: Unit economics
A10: Stripe trials | B10: No-card trial behaviour | C10: https://docs.stripe.com/billing/subscriptions/trials | D10: 2026-08-06 | E10: No payment method required | F10: Pilot model
A11: Twilio UK SMS | B11: SMS pricing | C11: https://www.twilio.com/en-us/sms/pricing/gb | D11: 2026-08-06 | E11: Per segment | F11: SMS credits
A12: Twilio character limits | B12: SMS segments | C12: https://www.twilio.com/docs/glossary/what-sms-character-limit | D12: 2026-08-06 | E12: 160/153 GSM-7; 70/67 UCS-2 | F12: Composer rules
A13: Resend pricing | B13: Email pricing | C13: https://resend.com/docs/knowledge-base/what-is-resend-pricing | D13: 2026-08-06 | E13: Marketing is contact-based | F13: Provider adapter
A14: Resend global Contacts | B14: Tenant risk | C14: https://resend.com/docs/dashboard/audiences/contacts | D14: 2026-08-06 | E14: Contacts global by email | F14: Do not hard-wire Broadcast Contacts
A15: Resend multi-tenant guidance | B15: Architecture | C15: https://resend.com/docs/knowledge-base/setting-up-resend-for-multi-tenants | D15: 2026-08-06 | E15: Shared reputation and aggregate limits | F15: Provider abstraction
... A20: Tummly terms | B20: Customer billing rules | C20: Tummly_Terms_and_Conditions (1).docx | D20: 2026-08-06 | E20: Supports VAT, credits, renewal and Shop | F20: Terms alignment
